lexical_analyzer/README.md
lexical_analyzer/__init__.py
lexical_analyzer/lexem.py
search_methods/README.md
search_methods/__init__.py
search_methods/diff_search_methods.py
search_methods/scripts/__init__.py
search_methods/scripts/lineare_probing_hash_table.py
search_methods/scripts/tree_node.py
2rage_py_challenges-0.1.3.dist-info/LICENSE
2rage_py_challenges-0.1.3.dist-info/METADATA
2rage_py_challenges-0.1.3.dist-info/WHEEL
2rage_py_challenges-0.1.3.dist-info/entry_points.txt
2rage_py_challenges-0.1.3.dist-info/RECORD
