Metadata-Version: 2.1
Name: 2rage-py-challenges
Version: 0.1.3
Summary: Some python challenges
License: MIT
Author: 2rage
Author-email: the2rage@icloud.com
Requires-Python: >=3.12,<4.0
Classifier: License :: OSI Approved :: MIT License
Classifier: Programming Language :: Python :: 3
Classifier: Programming Language :: Python :: 3.12
Requires-Dist: colorama (>=0.4.6,<0.5.0)
